zcatcher.py
zcatcher-0.4.0.dist-info/licenses/LICENSE
zcatcher-0.4.0.dist-info/METADATA
zcatcher-0.4.0.dist-info/WHEEL
zcatcher-0.4.0.dist-info/entry_points.txt
zcatcher-0.4.0.dist-info/top_level.txt
zcatcher-0.4.0.dist-info/RECORD
