Metadata-Version: 2.4
Name: zcatcher
Version: 0.4.0
Summary: Simple CLI to catch sleep, view stats, and export data
Author: Sleeptracker Maintainer
License-Expression: MIT
Requires-Python: >=3.8
License-File: LICENSE
Dynamic: license-file
